spangle/__init__.py
spangle/__main__.py
spangle/_internal/__init__.py
spangle/_internal/dispatcher.py
spangle/_internal/router.py
spangle/_internal/utils.py
spangle/api.py
spangle/blueprint.py
spangle/cli/__init__.py
spangle/cli/run.py
spangle/component.py
spangle/error_handler.py
spangle/exceptions.py
spangle/handler_protocols.py
spangle/models/__init__.py
spangle/models/http.py
spangle/models/websocket.py
spangle/parser.py
spangle/py.typed
spangle/testing.py
spangle/types.py
spangle-0.12.0.dist-info/entry_points.txt
spangle-0.12.0.dist-info/LICENSE
spangle-0.12.0.dist-info/WHEEL
spangle-0.12.0.dist-info/METADATA
spangle-0.12.0.dist-info/RECORD
