Metadata-Version: 2.1
Name: spangle
Version: 0.12.0
Summary: A small and flexible ASGI application framework for modern web.
Home-page: https://github.com/tkamenoko/spangle
License: MIT
Author: T.Kameyama
Author-email: tkamenoko@vivaldi.net
Requires-Python: >=3.9,<4.0
Classifier: Development Status :: 2 - Pre-Alpha
Classifier: Environment :: Web Environment
Classifier: Intended Audience :: Developers
Classifier: License :: OSI Approved :: MIT License
Classifier: Operating System :: OS Independent
Classifier: Programming Language :: JavaScript
Classifier: Programming Language :: Python :: 3
Classifier: Programming Language :: Python :: 3.9
Classifier: Programming Language :: Python :: Implementation :: CPython
Classifier: Topic :: Internet :: WWW/HTTP
Requires-Dist: addict (>=2.2.1,<3.0.0)
Requires-Dist: aiofiles (>=0.7.0,<0.8.0)
Requires-Dist: asgiref (>=3.4.1,<4.0.0)
Requires-Dist: chardet (>=4.0.0,<5.0.0)
Requires-Dist: httpx (>=0.21.1,<0.22.0)
Requires-Dist: jinja2 (>=3.0.1,<4.0.0)
Requires-Dist: multipart (>=0.2.4,<0.3.0)
Requires-Dist: parse (>=1.19.0,<2.0.0)
Requires-Dist: starlette (>=0.17.1,<0.18.0)
Requires-Dist: urllib3 (>=1.26.6,<2.0.0)
Project-URL: Documentation, https://tkamenoko.github.io/spangle/
Project-URL: Repository, https://github.com/tkamenoko/spangle
